tradingene/__init__.py
tradingene/algorithm_backtest/__init__.py
tradingene/algorithm_backtest/algorithm.py
tradingene/algorithm_backtest/backtest.py
tradingene/algorithm_backtest/cheat_backtest.py
tradingene/algorithm_backtest/cheat_position.py
tradingene/algorithm_backtest/environment.py
tradingene/algorithm_backtest/export.py
tradingene/algorithm_backtest/instrument.py
tradingene/algorithm_backtest/limits.py
tradingene/algorithm_backtest/position.py
tradingene/algorithm_backtest/price_event.py
tradingene/algorithm_backtest/time_event.py
tradingene/algorithm_backtest/tng.py
tradingene/algorithm_backtest/trade.py
tradingene/algorithm_backtest/trade_activity.py
tradingene/backtest_statistics/__init__.py
tradingene/backtest_statistics/backtest_statistics.py
tradingene/data/__init__.py
tradingene/data/data.py
tradingene/data/data_separation.py
tradingene/data/date_init.py
tradingene/data/load.py
tradingene/data/weekends.py
tradingene/data/__cached_history__/__init__.py
tradingene/examples/__init__.py
tradingene/examples/example1.py
tradingene/examples/example2.py
tradingene/examples/example3.py
tradingene/examples/first_alg.py
tradingene/examples/nn_2classes.py
tradingene/examples/nn_classes.py
tradingene/examples/nn_multi.py
tradingene/examples/nn_regression.py
tradingene/examples/nn_withindicators.py
tradingene/examples/nn_withscaler.py
tradingene/examples/svm.py
tradingene/ind/__init__.py
tradingene/ind/ind.py
tradingene/ind/spread_estimation_corwin_schultz.py
tradingene/ind/ti.py
tradingene/plot/__init__.py
tradingene/plot/plot.py
tradingene-0.0.dev35.dist-info/LICENSE
tradingene-0.0.dev35.dist-info/METADATA
tradingene-0.0.dev35.dist-info/WHEEL
tradingene-0.0.dev35.dist-info/top_level.txt
tradingene-0.0.dev35.dist-info/RECORD
