Metadata-Version: 2.1
Name: tradingene
Version: 0.0.dev35
Summary: Tradingene's package for algorithm backtest
Home-page: https://github.com/iburenko/tng
Author: Tradingene
Author-email: i.burenko@tradingene.com
License: MIT
Platform: UNKNOWN
Classifier: Programming Language :: Python :: 3.6
Classifier: License :: OSI Approved :: MIT License
Classifier: Operating System :: OS Independent
